{
  "type": "Collection",
  "id": "ESA_LUISA_HANPP_HARV_CROPLAND",
  "stac_version": "1.0.0",
  "description": "Contains HANPP_HARV_CROPLAND products at 1km resolution for the African continent from 2000-2020.",
  "links": [
    {
      "rel": "root",
      "href": "./collection.json",
      "type": "application/json",
      "title": "ESA LUISA - Continental HANPP_HARV_CROPLAND products for Africa at 1km resolution"
    },
    {
      "rel": "item",
      "href": "./ESA_LUISA_HANPP_HARV_CROPLAND/openEO_2000-01-01Z.json",
      "type": "application/json"
    },
    {
      "rel": "item",
      "href": "./ESA_LUISA_HANPP_HARV_CROPLAND/openEO_2001-01-01Z.json",
      "type": "application/json"
    },
    {
      "rel": "item",
      "href": "./ESA_LUISA_HANPP_HARV_CROPLAND/openEO_2002-01-01Z.json",
      "type": "application/json"
    },
    {
      "rel": "item",
      "href": "./ESA_LUISA_HANPP_HARV_CROPLAND/openEO_2003-01-01Z.json",
      "type": "application/json"
    },
    {
      "rel": "item",
      "href": "./ESA_LUISA_HANPP_HARV_CROPLAND/openEO_2004-01-01Z.json",
      "type": "application/json"
    },
    {
      "rel": "item",
      "href": "./ESA_LUISA_HANPP_HARV_CROPLAND/openEO_2005-01-01Z.json",
      "type": "application/json"
    },
    {
      "rel": "item",
      "href": "./ESA_LUISA_HANPP_HARV_CROPLAND/openEO_2006-01-01Z.json",
      "type": "application/json"
    },
    {
      "rel": "item",
      "href": "./ESA_LUISA_HANPP_HARV_CROPLAND/openEO_2007-01-01Z.json",
      "type": "application/json"
    },
    {
      "rel": "item",
      "href": "./ESA_LUISA_HANPP_HARV_CROPLAND/openEO_2008-01-01Z.json",
      "type": "application/json"
    },
    {
      "rel": "item",
      "href": "./ESA_LUISA_HANPP_HARV_CROPLAND/openEO_2009-01-01Z.json",
      "type": "application/json"
    },
    {
      "rel": "item",
      "href": "./ESA_LUISA_HANPP_HARV_CROPLAND/openEO_2010-01-01Z.json",
      "type": "application/json"
    },
    {
      "rel": "item",
      "href": "./ESA_LUISA_HANPP_HARV_CROPLAND/openEO_2011-01-01Z.json",
      "type": "application/json"
    },
    {
      "rel": "item",
      "href": "./ESA_LUISA_HANPP_HARV_CROPLAND/openEO_2012-01-01Z.json",
      "type": "application/json"
    },
    {
      "rel": "item",
      "href": "./ESA_LUISA_HANPP_HARV_CROPLAND/openEO_2013-01-01Z.json",
      "type": "application/json"
    },
    {
      "rel": "item",
      "href": "./ESA_LUISA_HANPP_HARV_CROPLAND/openEO_2014-01-01Z.json",
      "type": "application/json"
    },
    {
      "rel": "item",
      "href": "./ESA_LUISA_HANPP_HARV_CROPLAND/openEO_2015-01-01Z.json",
      "type": "application/json"
    },
    {
      "rel": "item",
      "href": "./ESA_LUISA_HANPP_HARV_CROPLAND/openEO_2016-01-01Z.json",
      "type": "application/json"
    },
    {
      "rel": "item",
      "href": "./ESA_LUISA_HANPP_HARV_CROPLAND/openEO_2017-01-01Z.json",
      "type": "application/json"
    },
    {
      "rel": "item",
      "href": "./ESA_LUISA_HANPP_HARV_CROPLAND/openEO_2018-01-01Z.json",
      "type": "application/json"
    },
    {
      "rel": "item",
      "href": "./ESA_LUISA_HANPP_HARV_CROPLAND/openEO_2019-01-01Z.json",
      "type": "application/json"
    }
  ],
  "stac_extensions": [
    "https://stac-extensions.github.io/item-assets/v1.0.0/schema.json",
    "https://stac-extensions.github.io/raster/v1.1.0/schema.json",
    "https://stac-extensions.github.io/classification/v1.0.0/schema.json",
    "https://stac-extensions.github.io/eo/v1.1.0/schema.json",
    "https://stac-extensions.github.io/datacube/v2.2.0/schema.json"
  ],
  "item_assets": {
    "hanpp_harv_crop": {
      "type": "image/tiff; application=geotiff",
      "title": "Human Appropriation of the Net Primary Production Harvest Cropland",
      "description": "Human Appropriation of the Net Primary Production Harvest Cropland",
      "roles": [
        "data"
      ],
      "eo:bands": [
        {
          "name": "hanpp_harv_crop",
          "description": "HANPP Harv Crop"
        }
      ]
    }
  },
  "cube:dimensions": {
    "x": {
      "type": "spatial",
      "extent": [
        -90,
        90
      ],
      "axis": "x",
      "reference_system": {
        "$schema": "https://proj.org/schemas/v0.7/projjson.schema.json",
        "type": "ProjectedCRS",
        "name": "WGS 84 / Pseudo-Mercator",
        "base_crs": {
          "name": "WGS 84",
          "datum_ensemble": {
            "name": "World Geodetic System 1984 ensemble",
            "members": [
              {
                "name": "World Geodetic System 1984 (Transit)",
                "id": {
                  "authority": "EPSG",
                  "code": 1166
                }
              },
              {
                "name": "World Geodetic System 1984 (G730)",
                "id": {
                  "authority": "EPSG",
                  "code": 1152
                }
              },
              {
                "name": "World Geodetic System 1984 (G873)",
                "id": {
                  "authority": "EPSG",
                  "code": 1153
                }
              },
              {
                "name": "World Geodetic System 1984 (G1150)",
                "id": {
                  "authority": "EPSG",
                  "code": 1154
                }
              },
              {
                "name": "World Geodetic System 1984 (G1674)",
                "id": {
                  "authority": "EPSG",
                  "code": 1155
                }
              },
              {
                "name": "World Geodetic System 1984 (G1762)",
                "id": {
                  "authority": "EPSG",
                  "code": 1156
                }
              },
              {
                "name": "World Geodetic System 1984 (G2139)",
                "id": {
                  "authority": "EPSG",
                  "code": 1309
                }
              },
              {
                "name": "World Geodetic System 1984 (G2296)",
                "id": {
                  "authority": "EPSG",
                  "code": 1383
                }
              }
            ],
            "ellipsoid": {
              "name": "WGS 84",
              "semi_major_axis": 6378137,
              "inverse_flattening": 298.257223563
            },
            "accuracy": "2.0",
            "id": {
              "authority": "EPSG",
              "code": 6326
            }
          },
          "coordinate_system": {
            "subtype": "ellipsoidal",
            "axis": [
              {
                "name": "Geodetic latitude",
                "abbreviation": "Lat",
                "direction": "north",
                "unit": "degree"
              },
              {
                "name": "Geodetic longitude",
                "abbreviation": "Lon",
                "direction": "east",
                "unit": "degree"
              }
            ]
          },
          "id": {
            "authority": "EPSG",
            "code": 4326
          }
        },
        "conversion": {
          "name": "Popular Visualisation Pseudo-Mercator",
          "method": {
            "name": "Popular Visualisation Pseudo Mercator",
            "id": {
              "authority": "EPSG",
              "code": 1024
            }
          },
          "parameters": [
            {
              "name": "Latitude of natural origin",
              "value": 0,
              "unit": "degree",
              "id": {
                "authority": "EPSG",
                "code": 8801
              }
            },
            {
              "name": "Longitude of natural origin",
              "value": 0,
              "unit": "degree",
              "id": {
                "authority": "EPSG",
                "code": 8802
              }
            },
            {
              "name": "False easting",
              "value": 0,
              "unit": "metre",
              "id": {
                "authority": "EPSG",
                "code": 8806
              }
            },
            {
              "name": "False northing",
              "value": 0,
              "unit": "metre",
              "id": {
                "authority": "EPSG",
                "code": 8807
              }
            }
          ]
        },
        "coordinate_system": {
          "subtype": "Cartesian",
          "axis": [
            {
              "name": "Easting",
              "abbreviation": "X",
              "direction": "east",
              "unit": "metre"
            },
            {
              "name": "Northing",
              "abbreviation": "Y",
              "direction": "north",
              "unit": "metre"
            }
          ]
        },
        "scope": "Web mapping and visualisation.",
        "area": "World between 85.06\u00b0S and 85.06\u00b0N.",
        "bbox": {
          "south_latitude": -85.06,
          "west_longitude": -180,
          "north_latitude": 85.06,
          "east_longitude": 180
        },
        "id": {
          "authority": "EPSG",
          "code": 3857
        }
      },
      "step": 1000
    },
    "y": {
      "type": "spatial",
      "extent": [
        -180,
        180
      ],
      "axis": "y",
      "reference_system": {
        "$schema": "https://proj.org/schemas/v0.7/projjson.schema.json",
        "type": "ProjectedCRS",
        "name": "WGS 84 / Pseudo-Mercator",
        "base_crs": {
          "name": "WGS 84",
          "datum_ensemble": {
            "name": "World Geodetic System 1984 ensemble",
            "members": [
              {
                "name": "World Geodetic System 1984 (Transit)",
                "id": {
                  "authority": "EPSG",
                  "code": 1166
                }
              },
              {
                "name": "World Geodetic System 1984 (G730)",
                "id": {
                  "authority": "EPSG",
                  "code": 1152
                }
              },
              {
                "name": "World Geodetic System 1984 (G873)",
                "id": {
                  "authority": "EPSG",
                  "code": 1153
                }
              },
              {
                "name": "World Geodetic System 1984 (G1150)",
                "id": {
                  "authority": "EPSG",
                  "code": 1154
                }
              },
              {
                "name": "World Geodetic System 1984 (G1674)",
                "id": {
                  "authority": "EPSG",
                  "code": 1155
                }
              },
              {
                "name": "World Geodetic System 1984 (G1762)",
                "id": {
                  "authority": "EPSG",
                  "code": 1156
                }
              },
              {
                "name": "World Geodetic System 1984 (G2139)",
                "id": {
                  "authority": "EPSG",
                  "code": 1309
                }
              },
              {
                "name": "World Geodetic System 1984 (G2296)",
                "id": {
                  "authority": "EPSG",
                  "code": 1383
                }
              }
            ],
            "ellipsoid": {
              "name": "WGS 84",
              "semi_major_axis": 6378137,
              "inverse_flattening": 298.257223563
            },
            "accuracy": "2.0",
            "id": {
              "authority": "EPSG",
              "code": 6326
            }
          },
          "coordinate_system": {
            "subtype": "ellipsoidal",
            "axis": [
              {
                "name": "Geodetic latitude",
                "abbreviation": "Lat",
                "direction": "north",
                "unit": "degree"
              },
              {
                "name": "Geodetic longitude",
                "abbreviation": "Lon",
                "direction": "east",
                "unit": "degree"
              }
            ]
          },
          "id": {
            "authority": "EPSG",
            "code": 4326
          }
        },
        "conversion": {
          "name": "Popular Visualisation Pseudo-Mercator",
          "method": {
            "name": "Popular Visualisation Pseudo Mercator",
            "id": {
              "authority": "EPSG",
              "code": 1024
            }
          },
          "parameters": [
            {
              "name": "Latitude of natural origin",
              "value": 0,
              "unit": "degree",
              "id": {
                "authority": "EPSG",
                "code": 8801
              }
            },
            {
              "name": "Longitude of natural origin",
              "value": 0,
              "unit": "degree",
              "id": {
                "authority": "EPSG",
                "code": 8802
              }
            },
            {
              "name": "False easting",
              "value": 0,
              "unit": "metre",
              "id": {
                "authority": "EPSG",
                "code": 8806
              }
            },
            {
              "name": "False northing",
              "value": 0,
              "unit": "metre",
              "id": {
                "authority": "EPSG",
                "code": 8807
              }
            }
          ]
        },
        "coordinate_system": {
          "subtype": "Cartesian",
          "axis": [
            {
              "name": "Easting",
              "abbreviation": "X",
              "direction": "east",
              "unit": "metre"
            },
            {
              "name": "Northing",
              "abbreviation": "Y",
              "direction": "north",
              "unit": "metre"
            }
          ]
        },
        "scope": "Web mapping and visualisation.",
        "area": "World between 85.06\u00b0S and 85.06\u00b0N.",
        "bbox": {
          "south_latitude": -85.06,
          "west_longitude": -180,
          "north_latitude": 85.06,
          "east_longitude": 180
        },
        "id": {
          "authority": "EPSG",
          "code": 3857
        }
      },
      "step": 1000
    }
  },
  "title": "ESA LUISA - Continental HANPP_HARV_CROPLAND products for Africa at 1km resolution",
  "extent": {
    "spatial": {
      "bbox": [
        [
          -17.754464804914278,
          -34.75557561203972,
          51.76019920086688,
          37.254463988800005
        ]
      ]
    },
    "temporal": {
      "interval": [
        [
          "2000-01-01T00:00:00Z",
          "2019-12-31T23:59:59Z"
        ]
      ]
    }
  },
  "license": "proprietary"
}