{
    "collection_id": "REPLACE_THIS--COLLECTION_ID",
    "title": "REPLACE_THIS--COLLECTION_TITLE",
    "description": "REPLACE_THIS--COLLECTION_DESCRIPTION",
    "instruments": [],
    "keywords": [],
    "mission": [],
    "platform": [],
    "providers": [
        {
            "name": "VITO",
            "roles": [
                "licensor",
                "processor",
                "producer"
            ],
            "url": "https://www.vito.be/"
        }
    ],
    "layout_strategy_item_template": "${collection}/{year}",
    "input_path_parser": {
        "classname": "DefaultInputPathParser",
        "parameters": {
            "regex_pattern": ".*/(?P<asset_type>MIN|MAX)/(?P<year>\\d{4})-(?P<month>\\d{2}).tif$",
            "period": "monthly"
        }
    },
    "item_assets": {
        "REPLACE_THIS--BAND_NAME": {
            "title": "REPLACE_THIS--BAND_NAME",
            "description": "REPLACE_THIS--BAND_DESCRIPTIOn",
            "eo_bands": [
                {
                    "name": "REPLACE_THIS--BAND_NAME",
                    "description": "REPLACE_THIS--BAND_DESCRIPTION",
                    "data_type": "float32",
                    "sampling": "area",
                    "spatial_resolution": 100
                }
            ]
        }
    },
    "overrides": {}
}
